universal_image_generator_mcp/__init__.py
universal_image_generator_mcp/__main__.py
universal_image_generator_mcp/bailian_provider.py
universal_image_generator_mcp/base_provider.py
universal_image_generator_mcp/gemini_provider.py
universal_image_generator_mcp/prompts.py
universal_image_generator_mcp/providers.py
universal_image_generator_mcp/server.py
universal_image_generator_mcp/utils.py
universal_image_generator_mcp/zhipuai_provider.py
universal_image_generator_mcp-0.1.2.dist-info/METADATA
universal_image_generator_mcp-0.1.2.dist-info/WHEEL
universal_image_generator_mcp-0.1.2.dist-info/entry_points.txt
universal_image_generator_mcp-0.1.2.dist-info/licenses/LICENSE
universal_image_generator_mcp-0.1.2.dist-info/RECORD
