Metadata-Version: 2.4
Name: universal-image-generator-mcp
Version: 0.1.2
Summary: Universal Image Generator MCP
Project-URL: Homepage, https://github.com/ECNU3D/universal-image-generator-mcp
Project-URL: Issues, https://github.com/ECNU3D/universal-image-generator-mcp/issues
Author-email: Tony Wang <shanghaishanghai@yeah.net>
License: MIT
License-File: LICENSE
Keywords: automation,http,llm,mcp
Requires-Python: >=3.11
Requires-Dist: build>=1.2.2.post1
Requires-Dist: fastmcp>=0.4.1
Requires-Dist: google-genai>=1.7.0
Requires-Dist: google>=3.0.0
Requires-Dist: pillow>=11.1.0
Requires-Dist: twine>=6.1.0
Requires-Dist: zhipuai>=2.1.5.20250708
